streamlitgo/__init__.py
streamlitgo/__main__.py
streamlitgo/cli.py
streamlitgo/config/stgo.py
streamlitgo-0.1.3.dist-info/METADATA
streamlitgo-0.1.3.dist-info/WHEEL
streamlitgo-0.1.3.dist-info/entry_points.txt
streamlitgo-0.1.3.dist-info/RECORD
